jwt_auditor.py
jwt_auditor-1.1.0.dist-info/METADATA
jwt_auditor-1.1.0.dist-info/WHEEL
jwt_auditor-1.1.0.dist-info/entry_points.txt
jwt_auditor-1.1.0.dist-info/top_level.txt
jwt_auditor-1.1.0.dist-info/RECORD
