Metadata-Version: 2.4
Name: jwt-auditor
Version: 1.1.0
Summary: Command-line tool for JWT security auditing
Author-email: Joas Santos <joas.santos@hackersec.com>
License: MIT
Requires-Python: >=3.8
Requires-Dist: cryptography
Requires-Dist: requests
